{
    "abstract": "The Mining Software Repositories community typically focuses on data from software configuration management tools, mailing lists, and bug tracking repositories to uncover interesting and actionable information about the evolution of software systems. However, the techniques employed and the challenges faced when mining are not restricted to these types of repositories. In this paper, we present an atypical dataset of software engineering conferences, containing historical data about the accepted papers and the composition of programme committees for eleven well-established conferences. The dataset (published on Github at https://github.com/tue-mdse/conferenceMetrics) can be used, e.g., by conference steering committees or programme committee chairs to assess their selection process and compare against other conferences in the field, or by prospective authors to decide in which conferences to publish.",
    "arxivId": null,
    "authors": [
        {
            "authorId": "2434621",
            "name": "Bogdan Vasilescu",
            "url": "https://www.semanticscholar.org/author/2434621"
        },
        {
            "authorId": "1747171",
            "name": "Alexander Serebrenik",
            "url": "https://www.semanticscholar.org/author/1747171"
        },
        {
            "authorId": "1794675",
            "name": "T. Mens",
            "url": "https://www.semanticscholar.org/author/1794675"
        }
    ],
    "citationVelocity": 0,
    "citations": [
        {
            "arxivId": null,
            "authors": [
                {
                    "authorId": "2317108143",
                    "name": "Vasilica Moldovan"
                },
                {
                    "authorId": "2317105776",
                    "name": "Simona Motogna"
                }
            ],
            "doi": "10.1145/3643785.3648492",
            "intent": [
                "background"
            ],
            "isInfluential": false,
            "paperId": "2e10776e1e9ed5730aae1fa6a1f5fe575c6ae364",
            "title": "Diversity of SE Conferences",
            "url": "https://www.semanticscholar.org/paper/2e10776e1e9ed5730aae1fa6a1f5fe575c6ae364",
            "venue": "2024 IEEE/ACM Workshop on Gender Equality, Diversity, and Inclusion in Software Engineering (GEICSE)",
            "year": 2024
        },
        {
            "arxivId": "2310.16132",
            "authors": [
                {
                    "authorId": "2261673315",
                    "name": "Aditya Shankar Narayanan"
                },
                {
                    "authorId": "1645254938",
                    "name": "Dheeraj Vagavolu"
                },
                {
                    "authorId": "2261672901",
                    "name": "Nancy A Day"
                },
                {
                    "authorId": "7274019",
                    "name": "M. Nagappan"
                }
            ],
            "doi": "10.48550/arXiv.2310.16132",
            "intent": [
                "background"
            ],
            "isInfluential": false,
            "paperId": "a873b464077081481ee3ad3010584ec24b39772f",
            "title": "Diversity in Software Engineering Conferences and Journals",
            "url": "https://www.semanticscholar.org/paper/a873b464077081481ee3ad3010584ec24b39772f",
            "venue": "ArXiv",
            "year": 2023
        },
        {
            "arxivId": "2207.08436",
            "authors": [
                {
                    "authorId": "151409813",
                    "name": "Zeinab Abou Khalil"
                },
                {
                    "authorId": "1682225",
                    "name": "Stefano Zacchiroli"
                }
            ],
            "doi": "10.1145/3544902.3546239",
            "intent": [
                "methodology",
                "background"
            ],
            "isInfluential": false,
            "paperId": "2937a015547b9fa16b26bb216938408bce2152ad",
            "title": "Software Artifact Mining in Software Engineering Conferences: A Meta-Analysis",
            "url": "https://www.semanticscholar.org/paper/2937a015547b9fa16b26bb216938408bce2152ad",
            "venue": "ESEM",
            "year": 2022
        },
        {
            "arxivId": "2204.03254",
            "authors": [
                {
                    "authorId": "151409813",
                    "name": "Zeinab Abou Khalil"
                },
                {
                    "authorId": "1682225",
                    "name": "Stefano Zacchiroli"
                }
            ],
            "doi": "10.1145/3524842.3528494",
            "intent": [
                "background",
                "result"
            ],
            "isInfluential": false,
            "paperId": "05b40a53c139563ddc200df43d11ef1b439ef00f",
            "title": "The General Index of Software Engineering Papers",
            "url": "https://www.semanticscholar.org/paper/05b40a53c139563ddc200df43d11ef1b439ef00f",
            "venue": "2022 IEEE/ACM 19th International Conference on Mining Software Repositories (MSR)",
            "year": 2022
        },
        {
            "arxivId": "2111.14583",
            "authors": [
                {
                    "authorId": "148430293",
                    "name": "Zoe Kotti"
                },
                {
                    "authorId": "2937511",
                    "name": "Konstantinos Kravvaritis"
                },
                {
                    "authorId": "41095366",
                    "name": "Konstantina Dritsa"
                },
                {
                    "authorId": "1740799",
                    "name": "D. Spinellis"
                }
            ],
            "doi": "10.1007/s10664-020-09834-7",
            "intent": [],
            "isInfluential": false,
            "paperId": "7889d09a8d6c1fc0089ad645b5fda0dae57a6314",
            "title": "Standing on shoulders or feet? An extended study on the usage of the MSR data papers",
            "url": "https://www.semanticscholar.org/paper/7889d09a8d6c1fc0089ad645b5fda0dae57a6314",
            "venue": "Empirical Software Engineering",
            "year": 2020
        },
        {
            "arxivId": null,
            "authors": [
                {
                    "authorId": "8722618",
                    "name": "Oscar Karnalim"
                },
                {
                    "authorId": "71228156",
                    "name": "Aulia Zahrina Qashri"
                }
            ],
            "doi": "10.2478/cait-2019-0022",
            "intent": [],
            "isInfluential": false,
            "paperId": "f6f12b128bd059e04652cd4230517d4d6665ce4f",
            "title": "Measuring the Significance of Writing Style for Recommending Where to Publish \u2013 A Case Study",
            "url": "https://www.semanticscholar.org/paper/f6f12b128bd059e04652cd4230517d4d6665ce4f",
            "venue": "Cybernetics and Information Technologies",
            "year": 2019
        },
        {
            "arxivId": null,
            "authors": [
                {
                    "authorId": "40021963",
                    "name": "S. Fathalla"
                },
                {
                    "authorId": "40466850",
                    "name": "C. Lange"
                },
                {
                    "authorId": "145044578",
                    "name": "S. Auer"
                }
            ],
            "doi": "10.1007/978-3-030-21348-0_28",
            "intent": [],
            "isInfluential": false,
            "paperId": "d467a85bd9bea3d53afe1dd25cf3e0ece687262e",
            "title": "EVENTSKG: A 5-Star Dataset of Top-Ranked Events in Eight Computer Science Communities",
            "url": "https://www.semanticscholar.org/paper/d467a85bd9bea3d53afe1dd25cf3e0ece687262e",
            "venue": "ESWC",
            "year": 2019
        },
        {
            "arxivId": null,
            "authors": [
                {
                    "authorId": "148430293",
                    "name": "Zoe Kotti"
                },
                {
                    "authorId": "1740799",
                    "name": "D. Spinellis"
                }
            ],
            "doi": "10.1109/MSR.2019.00085",
            "intent": [],
            "isInfluential": false,
            "paperId": "43148fabe2636026e07ca04974aff40d204bfb6b",
            "title": "Standing on Shoulders or Feet? The Usage of the MSR Data Papers",
            "url": "https://www.semanticscholar.org/paper/43148fabe2636026e07ca04974aff40d204bfb6b",
            "venue": "2019 IEEE/ACM 16th International Conference on Mining Software Repositories (MSR)",
            "year": 2019
        },
        {
            "arxivId": null,
            "authors": [
                {
                    "authorId": "40021963",
                    "name": "S. Fathalla"
                },
                {
                    "authorId": "40466850",
                    "name": "C. Lange"
                }
            ],
            "doi": "10.1007/978-3-319-98443-8_6",
            "intent": [],
            "isInfluential": false,
            "paperId": "49fb5f3d7ec9120bcab414f3a5167b78c84713f7",
            "title": "EVENTSKG: A Knowledge Graph Representation for Top-Prestigious Computer Science Events Metadata",
            "url": "https://www.semanticscholar.org/paper/49fb5f3d7ec9120bcab414f3a5167b78c84713f7",
            "venue": "ICCCI",
            "year": 2018
        },
        {
            "arxivId": "1706.09485",
            "authors": [
                {
                    "authorId": "38463326",
                    "name": "Dixin Luo"
                },
                {
                    "authorId": "34648261",
                    "name": "Kelly A. Lyons"
                }
            ],
            "doi": null,
            "intent": [
                "background"
            ],
            "isInfluential": false,
            "paperId": "e1d986af3d89fe18124b7896bc24fbb4cbd5c719",
            "title": "CASCONet: A Conference dataset",
            "url": "https://www.semanticscholar.org/paper/e1d986af3d89fe18124b7896bc24fbb4cbd5c719",
            "venue": "ArXiv",
            "year": 2017
        },
        {
            "arxivId": null,
            "authors": [
                {
                    "authorId": "40021963",
                    "name": "S. Fathalla"
                },
                {
                    "authorId": "40466850",
                    "name": "C. Lange"
                }
            ],
            "doi": "10.1007/978-3-030-01379-0_8",
            "intent": [
                "background"
            ],
            "isInfluential": false,
            "paperId": "452b022b1025a122913fc45726c3db886947ede3",
            "title": "EVENTS: A Dataset on the History of Top-Prestigious Events in Five Computer Science Communities",
            "url": "https://www.semanticscholar.org/paper/452b022b1025a122913fc45726c3db886947ede3",
            "venue": "SAVE-SD@WWW",
            "year": 2017
        },
        {
            "arxivId": null,
            "authors": [
                {
                    "authorId": "34820138",
                    "name": "Valerio Cosentino"
                },
                {
                    "authorId": "144272262",
                    "name": "Javier Luis C\u00e1novas Izquierdo"
                },
                {
                    "authorId": "1705375",
                    "name": "Jordi Cabot"
                }
            ],
            "doi": "10.1007/978-3-319-46397-1_28",
            "intent": [],
            "isInfluential": false,
            "paperId": "bc15e7264707f4fc646ce72fad1f8fcbbdbcabf9",
            "title": "MetaScience: An Holistic Approach for Research Modeling",
            "url": "https://www.semanticscholar.org/paper/bc15e7264707f4fc646ce72fad1f8fcbbdbcabf9",
            "venue": "ER",
            "year": 2016
        },
        {
            "arxivId": null,
            "authors": [
                {
                    "authorId": "30665018",
                    "name": "J. L. C\u00e1novas Izquierdo"
                },
                {
                    "authorId": "34820138",
                    "name": "Valerio Cosentino"
                },
                {
                    "authorId": "144220398",
                    "name": "Jordi Cabot"
                }
            ],
            "doi": "10.1007/s11192-016-2136-6",
            "intent": [
                "methodology"
            ],
            "isInfluential": false,
            "paperId": "4418e5dcdd4f281264b7020aea0a2e638c3f7780",
            "title": "Analysis of co-authorship graphs of CORE-ranked software conferences",
            "url": "https://www.semanticscholar.org/paper/4418e5dcdd4f281264b7020aea0a2e638c3f7780",
            "venue": "Scientometrics",
            "year": 2016
        },
        {
            "arxivId": "1608.08100",
            "authors": [
                {
                    "authorId": "2065190460",
                    "name": "George Mathew"
                },
                {
                    "authorId": "41152241",
                    "name": "Amritanshu Agrawal"
                },
                {
                    "authorId": "1703872",
                    "name": "T. Menzies"
                }
            ],
            "doi": "10.1109/TSE.2018.2870388",
            "intent": [
                "methodology"
            ],
            "isInfluential": false,
            "paperId": "c90c418cae116170442e906493841e017cd8ab27",
            "title": "Finding Trends in Software Research",
            "url": "https://www.semanticscholar.org/paper/c90c418cae116170442e906493841e017cd8ab27",
            "venue": "IEEE Transactions on Software Engineering",
            "year": 2016
        },
        {
            "arxivId": "1608.08176",
            "authors": [
                {
                    "authorId": "41152241",
                    "name": "Amritanshu Agrawal"
                },
                {
                    "authorId": "144188710",
                    "name": "Wei Fu"
                },
                {
                    "authorId": "1703872",
                    "name": "T. Menzies"
                }
            ],
            "doi": "10.1016/j.infsof.2018.02.005",
            "intent": [
                "background"
            ],
            "isInfluential": false,
            "paperId": "66a77e79e91575df5e687875d68ec55765e68d90",
            "title": "What is wrong with topic modeling? And how to fix it using search-based software engineering",
            "url": "https://www.semanticscholar.org/paper/66a77e79e91575df5e687875d68ec55765e68d90",
            "venue": "Inf. Softw. Technol.",
            "year": 2016
        },
        {
            "arxivId": null,
            "authors": [
                {
                    "authorId": "2065190460",
                    "name": "George Mathew"
                },
                {
                    "authorId": "41152241",
                    "name": "Amritanshu Agrawal"
                },
                {
                    "authorId": "1703872",
                    "name": "T. Menzies"
                }
            ],
            "doi": "10.1109/ICSE-C.2017.52",
            "intent": [
                "methodology"
            ],
            "isInfluential": false,
            "paperId": "3bda12aa2be5ed8a285118f829d750c127f75e98",
            "title": "Trends in Topics at SE Conferences (1993-2013)",
            "url": "https://www.semanticscholar.org/paper/3bda12aa2be5ed8a285118f829d750c127f75e98",
            "venue": "2017 IEEE/ACM 39th International Conference on Software Engineering Companion (ICSE-C)",
            "year": 2016
        },
        {
            "arxivId": null,
            "authors": [
                {
                    "authorId": "41152241",
                    "name": "Amritanshu Agrawal"
                },
                {
                    "authorId": "144188710",
                    "name": "Wei Fu"
                },
                {
                    "authorId": "1703872",
                    "name": "T. Menzies"
                }
            ],
            "doi": null,
            "intent": [],
            "isInfluential": false,
            "paperId": "e39078a3dcbcba8fd8b9bd0fc7a6a469a77a6d6c",
            "title": "What is Wrong with Topic Modeling? (and How to Fix it Using Search-based SE)",
            "url": "https://www.semanticscholar.org/paper/e39078a3dcbcba8fd8b9bd0fc7a6a469a77a6d6c",
            "venue": "ArXiv",
            "year": 2016
        },
        {
            "arxivId": null,
            "authors": [
                {
                    "authorId": "143874208",
                    "name": "B. Rodrigues"
                }
            ],
            "doi": null,
            "intent": [],
            "isInfluential": false,
            "paperId": "025a53f1cc27e61db00e3eb96622d315145b5d8b",
            "title": "PROPOSTA DE UM ARCABOU\u00c7O CONCEITUAL PARA A INTELIG\u00caNCIA ANAL\u00cdTICA NA ENGENHARIA DE SOFTWARE",
            "url": "https://www.semanticscholar.org/paper/025a53f1cc27e61db00e3eb96622d315145b5d8b",
            "venue": "",
            "year": 2016
        },
        {
            "arxivId": null,
            "authors": [
                {
                    "authorId": "145193818",
                    "name": "C. Bird"
                },
                {
                    "authorId": "1703872",
                    "name": "T. Menzies"
                },
                {
                    "authorId": "143609903",
                    "name": "Thomas Zimmermann"
                }
            ],
            "doi": "10.1016/c2012-0-07289-4",
            "intent": [],
            "isInfluential": false,
            "paperId": "67c1dced4e379676c1a6f65226e678d50c9541f1",
            "title": "The Art and Science of Analyzing Software Data",
            "url": "https://www.semanticscholar.org/paper/67c1dced4e379676c1a6f65226e678d50c9541f1",
            "venue": "ICSE 2015",
            "year": 2015
        },
        {
            "arxivId": null,
            "authors": [
                {
                    "authorId": "2434621",
                    "name": "Bogdan Vasilescu"
                },
                {
                    "authorId": "1747171",
                    "name": "Alexander Serebrenik"
                },
                {
                    "authorId": "1794675",
                    "name": "T. Mens"
                },
                {
                    "authorId": "1718306",
                    "name": "M. Brand"
                },
                {
                    "authorId": "2145189",
                    "name": "Ekaterina Pek"
                }
            ],
            "doi": "10.1016/J.SCICO.2014.01.016",
            "intent": [
                "methodology"
            ],
            "isInfluential": false,
            "paperId": "29d69d11a7a5364f871213e6a2476031b53246be",
            "title": "How healthy are software engineering conferences?",
            "url": "https://www.semanticscholar.org/paper/29d69d11a7a5364f871213e6a2476031b53246be",
            "venue": "Sci. Comput. Program.",
            "year": 2014
        },
        {
            "arxivId": null,
            "authors": [
                {
                    "authorId": "2434621",
                    "name": "Bogdan Vasilescu"
                }
            ],
            "doi": "10.1145/2591062.2591091",
            "intent": [
                "methodology"
            ],
            "isInfluential": false,
            "paperId": "1efdf05f979ebd7ff16baf7eac3348b5cb703d48",
            "title": "Human aspects, gamification, and social media in collaborative software engineering",
            "url": "https://www.semanticscholar.org/paper/1efdf05f979ebd7ff16baf7eac3348b5cb703d48",
            "venue": "ICSE Companion",
            "year": 2014
        },
        {
            "arxivId": null,
            "authors": [
                {
                    "authorId": "1794675",
                    "name": "T. Mens"
                },
                {
                    "authorId": "1747171",
                    "name": "Alexander Serebrenik"
                },
                {
                    "authorId": "2377431",
                    "name": "Anthony Cleve"
                }
            ],
            "doi": "10.1007/978-3-642-45398-4",
            "intent": [
                "background"
            ],
            "isInfluential": false,
            "paperId": "799169e956f803c4f26c923107abcc9453835bff",
            "title": "Evolving Software Systems",
            "url": "https://www.semanticscholar.org/paper/799169e956f803c4f26c923107abcc9453835bff",
            "venue": "Springer Berlin Heidelberg",
            "year": 2014
        },
        {
            "arxivId": null,
            "authors": [
                {
                    "authorId": "2060918972",
                    "name": "Robert Marco"
                },
                {
                    "authorId": "1834435",
                    "name": "N. Suryana"
                },
                {
                    "authorId": "47854818",
                    "name": "S. Sakinah"
                },
                {
                    "authorId": "2109918098",
                    "name": "Syed Ahmad"
                }
            ],
            "doi": null,
            "intent": [
                "methodology"
            ],
            "isInfluential": false,
            "paperId": "e4892cb7ee787b007b4362008cf1dc316b6f94a2",
            "title": "A SYSTEMATIC LITERATURE REVIEW ON METHODS FOR SOFTWARE EFFORT ESTIMATION",
            "url": "https://www.semanticscholar.org/paper/e4892cb7ee787b007b4362008cf1dc316b6f94a2",
            "venue": "",
            "year": 2019
        },
        {
            "arxivId": null,
            "authors": [
                {
                    "authorId": "9461040",
                    "name": "Maleknaz Nayebi"
                },
                {
                    "authorId": "145723974",
                    "name": "G. Ruhe"
                }
            ],
            "doi": "10.1016/B978-0-12-411519-4.00019-7",
            "intent": [
                "background"
            ],
            "isInfluential": false,
            "paperId": "4a0d96b8dfe0641dad3c07fc1b8dcb61789c46f1",
            "title": "Analytical Product Release Planning",
            "url": "https://www.semanticscholar.org/paper/4a0d96b8dfe0641dad3c07fc1b8dcb61789c46f1",
            "venue": "The Art and Science of Analyzing Software Data",
            "year": 2015
        },
        {
            "arxivId": null,
            "authors": [
                {
                    "authorId": "145543743",
                    "name": "V. Zaytsev"
                }
            ],
            "doi": null,
            "intent": [],
            "isInfluential": false,
            "paperId": "d5d5f1f33ce581a9a2599608f5751a97f2166e98",
            "title": "BibSLEIGH: Bibliography of Software (Language) Engineering in Generated Hypertext",
            "url": "https://www.semanticscholar.org/paper/d5d5f1f33ce581a9a2599608f5751a97f2166e98",
            "venue": "SATToSE",
            "year": 2015
        },
        {
            "arxivId": null,
            "authors": [
                {
                    "authorId": "2064082386",
                    "name": "Bn Bogdan Vasilescu"
                }
            ],
            "doi": null,
            "intent": [
                "methodology"
            ],
            "isInfluential": false,
            "paperId": "20856d1a4d151b643165a53f03a4ddc713f9f934",
            "title": "Social aspects of collaboration in online software communities",
            "url": "https://www.semanticscholar.org/paper/20856d1a4d151b643165a53f03a4ddc713f9f934",
            "venue": "",
            "year": 2014
        }
    ],
    "corpusId": 13362385,
    "doi": "10.1109/MSR.2013.6624051",
    "fieldsOfStudy": [
        "Engineering",
        "Computer Science"
    ],
    "influentialCitationCount": 0,
    "isOpenAccess": false,
    "isPublisherLicensed": true,
    "is_open_access": false,
    "is_publisher_licensed": true,
    "numCitedBy": 26,
    "numCiting": 18,
    "paperId": "24495773e6d696fe3705de86dfb4e133508eb237",
    "references": [
        {
            "arxivId": null,
            "authors": [
                {
                    "authorId": "2855002",
                    "name": "M. Goeminne"
                },
                {
                    "authorId": "1794675",
                    "name": "T. Mens"
                }
            ],
            "doi": "10.1016/J.SCICO.2011.11.004",
            "intent": [
                "methodology",
                "background"
            ],
            "isInfluential": false,
            "paperId": "0927dc66bc647ea249c731c76da4b0f17be52c2c",
            "title": "A comparison of identity merge algorithms for software repositories",
            "url": "https://www.semanticscholar.org/paper/0927dc66bc647ea249c731c76da4b0f17be52c2c",
            "venue": "Sci. Comput. Program.",
            "year": 2013
        },
        {
            "arxivId": null,
            "authors": [
                {
                    "authorId": "2434621",
                    "name": "Bogdan Vasilescu"
                },
                {
                    "authorId": "1729877",
                    "name": "A. Capiluppi"
                },
                {
                    "authorId": "1747171",
                    "name": "Alexander Serebrenik"
                }
            ],
            "doi": "10.1093/iwc/iwt047",
            "intent": [],
            "isInfluential": false,
            "paperId": "81b4b8e8ece82bf32d06872ab3bca2a42060fb52",
            "title": "Gender, Representation and Online Participation: A Quantitative Study of StackOverflow",
            "url": "https://www.semanticscholar.org/paper/81b4b8e8ece82bf32d06872ab3bca2a42060fb52",
            "venue": "2012 International Conference on Social Informatics",
            "year": 2012
        },
        {
            "arxivId": null,
            "authors": [
                {
                    "authorId": "2651759",
                    "name": "Erik Kouters"
                },
                {
                    "authorId": "2434621",
                    "name": "Bogdan Vasilescu"
                },
                {
                    "authorId": "1747171",
                    "name": "Alexander Serebrenik"
                },
                {
                    "authorId": "1718306",
                    "name": "M. Brand"
                }
            ],
            "doi": "10.1109/ICSM.2012.6405329",
            "intent": [],
            "isInfluential": false,
            "paperId": "14d2580c7d25ad3febd0330f268e7ded7c474557",
            "title": "Who's who in Gnome: Using LSA to merge software repository identities",
            "url": "https://www.semanticscholar.org/paper/14d2580c7d25ad3febd0330f268e7ded7c474557",
            "venue": "2012 28th IEEE International Conference on Software Maintenance (ICSM)",
            "year": 2012
        },
        {
            "arxivId": null,
            "authors": [
                {
                    "authorId": "1729877",
                    "name": "A. Capiluppi"
                },
                {
                    "authorId": "1747171",
                    "name": "Alexander Serebrenik"
                },
                {
                    "authorId": "36869703",
                    "name": "A. Youssef"
                }
            ],
            "doi": "10.1109/MSR.2012.6224288",
            "intent": [],
            "isInfluential": false,
            "paperId": "fd086b7365e262a44a201a9dc72260e91acd7766",
            "title": "Developing an h-index for OSS developers",
            "url": "https://www.semanticscholar.org/paper/fd086b7365e262a44a201a9dc72260e91acd7766",
            "venue": "2012 9th IEEE Working Conference on Mining Software Repositories (MSR)",
            "year": 2012
        },
        {
            "arxivId": null,
            "authors": [
                {
                    "authorId": "2434621",
                    "name": "Bogdan Vasilescu"
                },
                {
                    "authorId": "1747171",
                    "name": "Alexander Serebrenik"
                },
                {
                    "authorId": "1718306",
                    "name": "M. Brand"
                }
            ],
            "doi": "10.1109/ICSM.2011.6080798",
            "intent": [],
            "isInfluential": false,
            "paperId": "ef857efe3ef3f9af33b3e0e42d00bacc7bfbc20f",
            "title": "You can't control the unfamiliar: A study on the relations between aggregation techniques for software metrics",
            "url": "https://www.semanticscholar.org/paper/ef857efe3ef3f9af33b3e0e42d00bacc7bfbc20f",
            "venue": "2011 27th IEEE International Conference on Software Maintenance (ICSM)",
            "year": 2011
        },
        {
            "arxivId": null,
            "authors": [
                {
                    "authorId": "2102800",
                    "name": "Wouter Poncin"
                },
                {
                    "authorId": "1747171",
                    "name": "Alexander Serebrenik"
                },
                {
                    "authorId": "1718306",
                    "name": "M. Brand"
                }
            ],
            "doi": "10.1109/CSMR.2011.5",
            "intent": [],
            "isInfluential": false,
            "paperId": "707b7f4b3e01d5838cf14ef0452751ff1cf3cead",
            "title": "Process Mining Software Repositories",
            "url": "https://www.semanticscholar.org/paper/707b7f4b3e01d5838cf14ef0452751ff1cf3cead",
            "venue": "2011 15th European Conference on Software Maintenance and Reengineering",
            "year": 2011
        },
        {
            "arxivId": null,
            "authors": [
                {
                    "authorId": "1747171",
                    "name": "Alexander Serebrenik"
                },
                {
                    "authorId": "1718306",
                    "name": "M. Brand"
                }
            ],
            "doi": "10.1109/ICSM.2010.5609637",
            "intent": [],
            "isInfluential": false,
            "paperId": "437853723e7d7e8774c3b67b0c2d896167a5f04a",
            "title": "Theil index for aggregation of software metrics values",
            "url": "https://www.semanticscholar.org/paper/437853723e7d7e8774c3b67b0c2d896167a5f04a",
            "venue": "2010 IEEE International Conference on Software Maintenance",
            "year": 2010
        },
        {
            "arxivId": null,
            "authors": [
                {
                    "authorId": "143684601",
                    "name": "G. Robles"
                }
            ],
            "doi": "10.1109/MSR.2010.5463348",
            "intent": [
                "background",
                "methodology"
            ],
            "isInfluential": false,
            "paperId": "7cd1483cf03b3edbaceb8d278db155bbb9a65f9a",
            "title": "Replicating MSR: A study of the potential replicability of papers published in the Mining Software Repositories proceedings",
            "url": "https://www.semanticscholar.org/paper/7cd1483cf03b3edbaceb8d278db155bbb9a65f9a",
            "venue": "2010 7th IEEE Working Conference on Mining Software Repositories (MSR 2010)",
            "year": 2010
        },
        {
            "arxivId": null,
            "authors": [
                {
                    "authorId": "1422155236",
                    "name": "Michael Ley"
                }
            ],
            "doi": "10.14778/1687553.1687577",
            "intent": [
                "background"
            ],
            "isInfluential": false,
            "paperId": "7b92dd96065fcec0989d0ebcd3fec0b3cd6427d1",
            "title": "DBLP - Some Lessons Learned",
            "url": "https://www.semanticscholar.org/paper/7b92dd96065fcec0989d0ebcd3fec0b3cd6427d1",
            "venue": "Proc. VLDB Endow.",
            "year": 2009
        },
        {
            "arxivId": null,
            "authors": [
                {
                    "authorId": "119700081",
                    "name": "A. Hassan"
                }
            ],
            "doi": "10.1109/FOSM.2008.4659248",
            "intent": [],
            "isInfluential": false,
            "paperId": "0eeb699fc1b8eb752319053084d0fb77a63a0e84",
            "title": "The road ahead for Mining Software Repositories",
            "url": "https://www.semanticscholar.org/paper/0eeb699fc1b8eb752319053084d0fb77a63a0e84",
            "venue": "2008 Frontiers of Software Maintenance",
            "year": 2008
        },
        {
            "arxivId": null,
            "authors": [
                {
                    "authorId": "145193818",
                    "name": "C. Bird"
                },
                {
                    "authorId": "2047076",
                    "name": "A. Gourley"
                },
                {
                    "authorId": "1730296",
                    "name": "Premkumar T. Devanbu"
                },
                {
                    "authorId": "40136143",
                    "name": "Michael Gertz"
                },
                {
                    "authorId": "145014504",
                    "name": "A. Swaminathan"
                }
            ],
            "doi": "10.1145/1137983.1138016",
            "intent": [],
            "isInfluential": false,
            "paperId": "ef17134a558ca3c70d3bd50670835b947f033afb",
            "title": "Mining email social networks",
            "url": "https://www.semanticscholar.org/paper/ef17134a558ca3c70d3bd50670835b947f033afb",
            "venue": "MSR '06",
            "year": 2006
        },
        {
            "arxivId": null,
            "authors": [
                {
                    "authorId": "143684601",
                    "name": "G. Robles"
                },
                {
                    "authorId": "1397826059",
                    "name": "Jesus M. Gonzalez-Barahona"
                }
            ],
            "doi": "10.1145/1082983.1083162",
            "intent": [
                "background"
            ],
            "isInfluential": false,
            "paperId": "f33ee0b62425fc44baa2faaa739983b7327883dc",
            "title": "Developer identification methods for integrated data from various sources",
            "url": "https://www.semanticscholar.org/paper/f33ee0b62425fc44baa2faaa739983b7327883dc",
            "venue": "ACM SIGSOFT Softw. Eng. Notes",
            "year": 2005
        },
        {
            "arxivId": null,
            "authors": [
                {
                    "authorId": "144890499",
                    "name": "A. Hassan"
                },
                {
                    "authorId": "144345125",
                    "name": "R. Holt"
                }
            ],
            "doi": "10.1109/WCRE.2004.37",
            "intent": [],
            "isInfluential": false,
            "paperId": "7f70b6639f5fabc494be7a43b03da97dcf7e1e6e",
            "title": "The small world of software reverse engineering",
            "url": "https://www.semanticscholar.org/paper/7f70b6639f5fabc494be7a43b03da97dcf7e1e6e",
            "venue": "11th Working Conference on Reverse Engineering",
            "year": 2004
        },
        {
            "arxivId": null,
            "authors": [
                {
                    "authorId": "1720203",
                    "name": "Tarja Syst\u00e4"
                },
                {
                    "authorId": "2886428",
                    "name": "Maarit Harsu"
                },
                {
                    "authorId": "1775770",
                    "name": "K. Koskimies"
                }
            ],
            "doi": null,
            "intent": [
                "background"
            ],
            "isInfluential": false,
            "paperId": "5a99289403465289a2a5d9dee42599daf35a7aa4",
            "title": "Inbreeding in Software Engineering Conferences",
            "url": "https://www.semanticscholar.org/paper/5a99289403465289a2a5d9dee42599daf35a7aa4",
            "venue": "",
            "year": 2010
        },
        {
            "arxivId": null,
            "authors": [
                {
                    "authorId": "144334554",
                    "name": "J. Crowcroft"
                },
                {
                    "authorId": "145128122",
                    "name": "S. Keshav"
                },
                {
                    "authorId": "1708241",
                    "name": "N. McKeown"
                }
            ],
            "doi": "10.1145/1435417.1435430",
            "intent": [
                "background"
            ],
            "isInfluential": false,
            "paperId": "d8ed4b6e71db411a5c221a631a513ad43db48808",
            "title": "ViewpointScaling the academic publication process to internet scale",
            "url": "https://www.semanticscholar.org/paper/d8ed4b6e71db411a5c221a631a513ad43db48808",
            "venue": "CACM",
            "year": 2009
        },
        {
            "arxivId": null,
            "authors": [
                {
                    "authorId": "71795491",
                    "name": "Rick. Copeland"
                }
            ],
            "doi": null,
            "intent": [],
            "isInfluential": false,
            "paperId": "9eecfa9e28c3e96bad7de72af8da8e5eef202600",
            "title": "Essential SQLAlchemy",
            "url": "https://www.semanticscholar.org/paper/9eecfa9e28c3e96bad7de72af8da8e5eef202600",
            "venue": "",
            "year": 2008
        },
        {
            "arxivId": null,
            "authors": [],
            "doi": null,
            "intent": [],
            "isInfluential": false,
            "paperId": "",
            "title": "Simple h-index estimation",
            "url": "",
            "venue": "Simple h-index estimation",
            "year": 2013
        },
        {
            "arxivId": null,
            "authors": [],
            "doi": null,
            "intent": [],
            "isInfluential": false,
            "paperId": "",
            "title": "The DBLP computer science bibliography",
            "url": "",
            "venue": "The DBLP computer science bibliography",
            "year": 2013
        }
    ],
    "s2FieldsOfStudy": [
        {
            "category": "Engineering",
            "source": "external"
        },
        {
            "category": "Computer Science",
            "source": "external"
        },
        {
            "category": "Computer Science",
            "source": "s2-fos-model"
        }
    ],
    "title": "A historical dataset of software engineering conferences",
    "topics": [],
    "url": "https://www.semanticscholar.org/paper/24495773e6d696fe3705de86dfb4e133508eb237",
    "venue": "IEEE Working Conference on Mining Software Repositories",
    "year": 2013
}